{
    "a42ae01e-fa94-8dc1-c170-8943b01db2a0": {
        "name": "FlexLayoutCol",
        "guid": "a42ae01e-fa94-8dc1-c170-8943b01db2a0",
        "template": "<div fxLayout=\"column\" %style% %class% %fxFlex% %fxLayoutWrap% %fxLayoutGap% %fxLayoutAlign% %fxShow% %fxHide% %bCustomProps%></div>",
        "designerTemplate": "<div class=\"column drop bkeeper-container-label\"></div>",
        "paletteTemplate": "Flex Layout Column",
        "templateUrl": "https://github.com/angular/flex-layout/wiki/fxLayout-API",
        "htmlAttributes": [
            {
                "0": false,
                "_key": "style",
                "_value": "padding:10px",
                "_type": "kv",
                "_attrDef": "p"
            },
            {
                "1": false,
                "_key": "class",
                "_value": "",
                "_type": "kv",
                "_attrDef": "p"
            },
            {
                "2": false,
                "_key": "fxFlex",
                "_value": "100",
                "_type": "kv",
                "_attrDef": "p"
            },
            {
                "3": false,
                "_key": "fxLayoutWrap",
                "_value": "",
                "_type": "kv",
                "_attrDef": "p"
            },
            {
                "4": false,
                "_key": "fxLayoutGap",
                "_value": "",
                "_type": "kv",
                "_attrDef": "p"
            },
            {
                "5": false,
                "_key": "fxLayoutAlign",
                "_value": "",
                "_type": "kv",
                "_attrDef": "p"
            },
            {
                "6": false,
                "_key": "fxShow",
                "_value": "true",
                "_type": "kv",
                "_attrDef": "p"
            },
            {
                "7": false,
                "_key": "fxHide",
                "_value": "false",
                "_type": "kv",
                "_attrDef": "p"
            }
        ],
        "type": 1
    },
    "92846ecc-ce58-957f-cfd6-9551c9155cd0": {
        "name": "FlexLayoutRow",
        "guid": "92846ecc-ce58-957f-cfd6-9551c9155cd0",
        "template": "<div fxLayout=\"row\" %style% %class% %fxFlex% %fxLayoutWrap% %fxLayoutGap% %fxLayoutAlign% %fxShow% %fxHide% %bCustomProps%></div>",
        "designerTemplate": "<div class=\"row drop bkeeper-container-label\"></div>",
        "paletteTemplate": "Flex Layout Row",
        "templateUrl": "https://github.com/angular/flex-layout/wiki/fxLayout-API",
        "htmlAttributes": [
            {
                "_key": "style",
                "_value": "",
                "_type": "kv",
                "_attrDef": "p"
            },
            {
                "1": false,
                "_key": "class",
                "_value": "",
                "_type": "kv",
                "_attrDef": "p"
            },
            {
                "2": false,
                "_key": "fxFlex",
                "_value": "",
                "_type": "kv",
                "_attrDef": "p"
            },
            {
                "_key": "fxLayoutWrap",
                "_value": "",
                "_type": "kv",
                "_attrDef": "p"
            },
            {
                "4": false,
                "_key": "fxLayoutGap",
                "_value": "",
                "_type": "kv",
                "_attrDef": "p"
            },
            {
                "5": false,
                "_key": "fxLayoutAlign",
                "_value": "start",
                "_type": "kv",
                "_attrDef": "p"
            },
            {
                "6": false,
                "_key": "fxShow",
                "_value": "true",
                "_type": "kv",
                "_attrDef": "p"
            },
            {
                "7": false,
                "_key": "fxHide",
                "_value": "false",
                "_type": "kv",
                "_attrDef": "p"
            },
            {
                "_key": "fxFlex.xs",
                "_value": "none",
                "_type": "kv",
                "_attrDef": "c"
            },
            {
                "_key": "*ngIf",
                "_value": "false",
                "_type": "kv",
                "_attrDef": "c"
            }
        ],
        "type": 1
    },
    "870b14f7-5936-9acb-b387-ef07adebb2b4": {
        "name": "NG-Toolbar",
        "guid": "870b14f7-5936-9acb-b387-ef07adebb2b4",
        "template": "<mat-toolbar %bCustomProps% %color% %style% %class%>%content%</mat-toolbar>",
        "designerTemplate": "<div class=\"ad-toolbar-border ad-toolbars drop row\"></div>",
        "paletteTemplate": "Toolbar",
        "templateUrl": "https://material.angular.io/components/toolbar/overview",
        "htmlAttributes": [
            {
                "0": false,
                "_key": "style",
                "_value": "",
                "_type": "kv",
                "_attrDef": "p"
            },
            {
                "1": false,
                "_key": "class",
                "_value": "toolbar2",
                "_type": "kv",
                "_attrDef": "p"
            },
            {
                "2": false,
                "_key": "color",
                "_value": "",
                "_type": "kv",
                "_attrDef": "p"
            },
            {
                "3": false,
                "_key": "content",
                "_value": "",
                "_type": "a",
                "_attrDef": "p"
            },
            {
                "_key": "ngClass.xs",
                "_value": "logoxs",
                "_type": "kv",
                "_attrDef": "c"
            }
        ],
        "type": 6
    },
    "38d4e7fd-d3c1-e312-12b0-89b6cb5c1a68": {
        "name": "FlexLayoutCol",
        "guid": "38d4e7fd-d3c1-e312-12b0-89b6cb5c1a68",
        "template": "<div fxLayout=\"column\" %style% %class% %fxFlex% %fxLayoutWrap% %fxLayoutGap% %fxLayoutAlign% %fxShow% %fxHide% %bCustomProps%></div>",
        "designerTemplate": "<div class=\"column drop bkeeper-container-label\"></div>",
        "paletteTemplate": "Flex Layout Column",
        "templateUrl": "https://github.com/angular/flex-layout/wiki/fxLayout-API",
        "htmlAttributes": [
            {
                "0": false,
                "_key": "style",
                "_value": "",
                "_type": "kv",
                "_attrDef": "p"
            },
            {
                "1": false,
                "_key": "class",
                "_value": "",
                "_type": "kv",
                "_attrDef": "p"
            },
            {
                "2": false,
                "_key": "fxFlex",
                "_value": "50",
                "_type": "kv",
                "_attrDef": "p"
            },
            {
                "3": false,
                "_key": "fxLayoutWrap",
                "_value": "",
                "_type": "kv",
                "_attrDef": "p"
            },
            {
                "4": false,
                "_key": "fxLayoutGap",
                "_value": "",
                "_type": "kv",
                "_attrDef": "p"
            },
            {
                "5": false,
                "_key": "fxLayoutAlign",
                "_value": "start",
                "_type": "kv",
                "_attrDef": "p"
            },
            {
                "6": false,
                "_key": "fxShow",
                "_value": "true",
                "_type": "kv",
                "_attrDef": "p"
            },
            {
                "7": false,
                "_key": "fxHide",
                "_value": "false",
                "_type": "kv",
                "_attrDef": "p"
            }
        ],
        "type": 1
    },
    "2484755a-a219-153b-7b2d-83ad07554a64": {
        "name": "FlexLayoutRow",
        "guid": "2484755a-a219-153b-7b2d-83ad07554a64",
        "template": "<div fxLayout=\"row\" %style% %class% %fxFlex% %fxLayoutWrap% %fxLayoutGap% %fxLayoutAlign% %fxShow% %fxHide% %bCustomProps%></div>",
        "designerTemplate": "<div class=\"row drop bkeeper-container-label\"></div>",
        "paletteTemplate": "Flex Layout Row",
        "templateUrl": "https://github.com/angular/flex-layout/wiki/fxLayout-API",
        "htmlAttributes": [
            {
                "_key": "style",
                "_value": "",
                "_type": "kv",
                "_attrDef": "p"
            },
            {
                "1": false,
                "_key": "class",
                "_value": "",
                "_type": "kv",
                "_attrDef": "p"
            },
            {
                "2": false,
                "_key": "fxFlex",
                "_value": "100",
                "_type": "kv",
                "_attrDef": "p"
            },
            {
                "_key": "fxLayoutWrap",
                "_value": "",
                "_type": "kv",
                "_attrDef": "p"
            },
            {
                "_key": "fxLayoutGap",
                "_value": "",
                "_type": "kv",
                "_attrDef": "p"
            },
            {
                "5": false,
                "_key": "fxLayoutAlign",
                "_value": "start start",
                "_type": "kv",
                "_attrDef": "p"
            },
            {
                "6": false,
                "_key": "fxShow",
                "_value": "true",
                "_type": "kv",
                "_attrDef": "p"
            },
            {
                "_key": "fxHide",
                "_value": "false",
                "_type": "kv",
                "_attrDef": "p"
            }
        ],
        "type": 1
    },
    "f8471e20-f497-e3a0-e0b9-119cde99b26b": {
        "name": "NG-image",
        "guid": "f8471e20-f497-e3a0-e0b9-119cde99b26b",
        "template": "<img %imgSrc% %alt% %style% %bCustomProps% %class%>",
        "designerTemplate": "<div class=\"ad-image-component ad-charts-border ad-charts-align bkeeper-container-label\"></div>",
        "paletteTemplate": "Image",
        "templateUrl": "https://www.w3schools.com/html/html_images.asp",
        "htmlAttributes": [
            {
                "_key": "style",
                "_value": "",
                "_type": "kv",
                "_attrDef": "p"
            },
            {
                "1": false,
                "_key": "class",
                "_value": "logo",
                "_type": "kv",
                "_attrDef": "p"
            },
            {
                "2": false,
                "_key": "imgSrc",
                "_value": "Web/logo.png",
                "_type": "kv",
                "_attrDef": "p"
            },
            {
                "_key": "alt",
                "_value": "",
                "_type": "kv",
                "_attrDef": "p"
            }
        ],
        "type": 5
    },
    "d19febf9-9678-683a-5d7c-74850904e5c9": {
        "name": "NG-Paragraph",
        "guid": "d19febf9-9678-683a-5d7c-74850904e5c9",
        "template": "<p %bCustomProps% %style% %class%>%text%</p>",
        "designerTemplate": "<div class=\"ad-header-elements ad-h3\">p</div>",
        "paletteTemplate": "Paragraph",
        "templateUrl": "https://www.w3schools.com/tags/tag_p.asp",
        "htmlAttributes": [
            {
                "_key": "style",
                "_value": "",
                "_type": "kv",
                "_attrDef": "p"
            },
            {
                "1": false,
                "_key": "class",
                "_value": "",
                "_type": "kv",
                "_attrDef": "p"
            },
            {
                "2": false,
                "_key": "text",
                "_value": "ROOST",
                "_type": "a",
                "_attrDef": "p"
            }
        ],
        "type": 5
    },
    "5c5ba4eb-4d72-d514-458c-f4e4af4bc30e": {
        "name": "NG-RaisedButton",
        "guid": "5c5ba4eb-4d72-d514-458c-f4e4af4bc30e",
        "template": "<button mat-raised-button %style% %class% %bCustomProps% %color% %(click)%>%buttonname%</button>",
        "designerTemplate": "<div class=\"ad-raised-button\"></div>",
        "paletteTemplate": "Raised Button",
        "templateUrl": "https://material.angular.io/components/button/overview",
        "htmlAttributes": [
            {
                "0": false,
                "_key": "style",
                "_value": "height: 41px !important;      margin-top: 8%;      ",
                "_type": "kv",
                "_attrDef": "p"
            },
            {
                "1": false,
                "_key": "class",
                "_value": "rent",
                "_type": "kv",
                "_attrDef": "p"
            },
            {
                "2": false,
                "_key": "buttonname",
                "_value": "RENT",
                "_type": "a",
                "_attrDef": "p"
            },
            {
                "3": false,
                "_key": "color",
                "_value": "accent",
                "_type": "kv",
                "_attrDef": "p"
            },
            {
                "4": false,
                "_key": "(click)",
                "_value": "",
                "_type": "kv",
                "_attrDef": "p"
            }
        ],
        "type": 5
    },
    "fd3e24e5-a724-3e89-69f3-9e7e0734028e": {
        "name": "HTML",
        "guid": "fd3e24e5-a724-3e89-69f3-9e7e0734028e",
        "template": "%html%",
        "designerTemplate": "<div class=\"ad-lists bkeeper-container-label bkeeper-general-css\" b-props=\"html-editor\"><i style=\"font-size: 37px;line-height: 2;padding: 1px;\" class=\"material-icons\">code</i></div>",
        "paletteTemplate": "HTML",
        "templateUrl": "",
        "htmlAttributes": [
            {
                "_key": "style",
                "_value": "",
                "_type": "kv",
                "_attrDef": "p"
            },
            {
                "_key": "class",
                "_value": "",
                "_type": "kv",
                "_attrDef": "p"
            },
            {
                "_key": "html",
                "_value": "<bh-carousel [imageData]=\"imageData\" [limitImage]=\"limit\" style=\"width:100%\" *ngIf=\"imageData\"></bh-carousel>",
                "_type": "a",
                "_attrDef": "p"
            }
        ],
        "type": 7
    },
    "97383246-2514-ea41-df4c-a1e4233c6e6c": {
        "name": "FlexLayoutRow",
        "guid": "97383246-2514-ea41-df4c-a1e4233c6e6c",
        "template": "<div fxLayout=\"row\" %style% %class% %fxFlex% %fxLayoutWrap% %fxLayoutGap% %fxLayoutAlign% %fxShow% %fxHide% %bCustomProps%></div>",
        "designerTemplate": "<div class=\"row drop bkeeper-container-label\"></div>",
        "paletteTemplate": "Flex Layout Row",
        "templateUrl": "https://github.com/angular/flex-layout/wiki/fxLayout-API",
        "htmlAttributes": [
            {
                "_key": "style",
                "_value": "",
                "_type": "kv",
                "_attrDef": "p"
            },
            {
                "1": false,
                "_key": "class",
                "_value": "",
                "_type": "kv",
                "_attrDef": "p"
            },
            {
                "2": false,
                "_key": "fxFlex",
                "_value": "",
                "_type": "kv",
                "_attrDef": "p"
            },
            {
                "3": false,
                "_key": "fxLayoutWrap",
                "_value": "",
                "_type": "kv",
                "_attrDef": "p"
            },
            {
                "_key": "fxLayoutGap",
                "_value": "",
                "_type": "kv",
                "_attrDef": "p"
            },
            {
                "5": false,
                "_key": "fxLayoutAlign",
                "_value": "",
                "_type": "kv",
                "_attrDef": "p"
            },
            {
                "6": false,
                "_key": "fxShow",
                "_value": "true",
                "_type": "kv",
                "_attrDef": "p"
            },
            {
                "7": false,
                "_key": "fxHide",
                "_value": "false",
                "_type": "kv",
                "_attrDef": "p"
            }
        ],
        "type": 1
    },
    "6842eca7-ff14-af42-ee60-a4a5a62a4f8e": {
        "name": "NG-Toolbar",
        "guid": "6842eca7-ff14-af42-ee60-a4a5a62a4f8e",
        "template": "<mat-toolbar %bCustomProps% %color% %style% %class%>%content%</mat-toolbar>",
        "designerTemplate": "<div class=\"ad-toolbar-border ad-toolbars drop row\"></div>",
        "paletteTemplate": "Toolbar",
        "templateUrl": "https://material.angular.io/components/toolbar/overview",
        "htmlAttributes": [
            {
                "0": false,
                "_key": "style",
                "_value": "background-color: #3c4ca9;",
                "_type": "kv",
                "_attrDef": "p"
            },
            {
                "1": true,
                "_key": "class",
                "_value": "toolbar1",
                "_type": "kv",
                "_attrDef": "p"
            },
            {
                "2": false,
                "_key": "color",
                "_value": "",
                "_type": "kv",
                "_attrDef": "p"
            },
            {
                "3": true,
                "_key": "content",
                "_value": "",
                "_type": "a",
                "_attrDef": "p"
            }
        ],
        "type": 6
    },
    "ace0fe2a-70cb-031c-a1df-2c111e05fffa": {
        "name": "FlexLayoutCol",
        "guid": "ace0fe2a-70cb-031c-a1df-2c111e05fffa",
        "template": "<div fxLayout=\"column\" %style% %class% %fxFlex% %fxLayoutWrap% %fxLayoutGap% %fxLayoutAlign% %fxShow% %fxHide% %bCustomProps%></div>",
        "designerTemplate": "<div class=\"column drop bkeeper-container-label\"></div>",
        "paletteTemplate": "Flex Layout Column",
        "templateUrl": "https://github.com/angular/flex-layout/wiki/fxLayout-API",
        "htmlAttributes": [
            {
                "_key": "style",
                "_value": "",
                "_type": "kv",
                "_attrDef": "p"
            },
            {
                "1": false,
                "_key": "class",
                "_value": "",
                "_type": "kv",
                "_attrDef": "p"
            },
            {
                "2": false,
                "_key": "fxFlex",
                "_value": "50",
                "_type": "kv",
                "_attrDef": "p"
            },
            {
                "_key": "fxLayoutWrap",
                "_value": "",
                "_type": "kv",
                "_attrDef": "p"
            },
            {
                "_key": "fxLayoutGap",
                "_value": "",
                "_type": "kv",
                "_attrDef": "p"
            },
            {
                "5": false,
                "_key": "fxLayoutAlign",
                "_value": "start start",
                "_type": "kv",
                "_attrDef": "p"
            },
            {
                "6": false,
                "_key": "fxShow",
                "_value": "true",
                "_type": "kv",
                "_attrDef": "p"
            },
            {
                "_key": "fxHide",
                "_value": "false",
                "_type": "kv",
                "_attrDef": "p"
            }
        ],
        "type": 1
    },
    "7c8ee6f3-48cc-2cc1-9f47-7c35a6e65d3a": {
        "name": "FlexLayoutCol",
        "guid": "7c8ee6f3-48cc-2cc1-9f47-7c35a6e65d3a",
        "template": "<div fxLayout=\"column\" %style% %class% %fxFlex% %fxLayoutWrap% %fxLayoutGap% %fxLayoutAlign% %fxShow% %fxHide% %bCustomProps%></div>",
        "designerTemplate": "<div class=\"column drop bkeeper-container-label\"></div>",
        "paletteTemplate": "Flex Layout Column",
        "templateUrl": "https://github.com/angular/flex-layout/wiki/fxLayout-API",
        "htmlAttributes": [
            {
                "0": false,
                "_key": "style",
                "_value": "",
                "_type": "kv",
                "_attrDef": "p"
            },
            {
                "1": false,
                "_key": "class",
                "_value": "",
                "_type": "kv",
                "_attrDef": "p"
            },
            {
                "2": false,
                "_key": "fxFlex",
                "_value": "50",
                "_type": "kv",
                "_attrDef": "p"
            },
            {
                "3": false,
                "_key": "fxLayoutWrap",
                "_value": "",
                "_type": "kv",
                "_attrDef": "p"
            },
            {
                "4": false,
                "_key": "fxLayoutGap",
                "_value": "",
                "_type": "kv",
                "_attrDef": "p"
            },
            {
                "5": false,
                "_key": "fxLayoutAlign",
                "_value": "end end",
                "_type": "kv",
                "_attrDef": "p"
            },
            {
                "6": false,
                "_key": "fxShow",
                "_value": "true",
                "_type": "kv",
                "_attrDef": "p"
            },
            {
                "7": false,
                "_key": "fxHide",
                "_value": "false",
                "_type": "kv",
                "_attrDef": "p"
            },
            {
                "8": false,
                "_key": "fxHide.xs",
                "_value": "true",
                "_type": "kv",
                "_attrDef": "c"
            },
            {
                "9": false,
                "_key": "fxHide.sm",
                "_value": "true",
                "_type": "kv",
                "_attrDef": "c"
            }
        ],
        "type": 1
    },
    "ca9e5bd3-ddff-8f04-b551-b5722f1d9184": {
        "name": "FlexLayoutRow",
        "guid": "ca9e5bd3-ddff-8f04-b551-b5722f1d9184",
        "template": "<div fxLayout=\"row\" %style% %class% %fxFlex% %fxLayoutWrap% %fxLayoutGap% %fxLayoutAlign% %fxShow% %fxHide% %bCustomProps%></div>",
        "designerTemplate": "<div class=\"row drop bkeeper-container-label\"></div>",
        "paletteTemplate": "Flex Layout Row",
        "templateUrl": "https://github.com/angular/flex-layout/wiki/fxLayout-API",
        "htmlAttributes": [
            {
                "_key": "style",
                "_value": "",
                "_type": "kv",
                "_attrDef": "p"
            },
            {
                "1": false,
                "_key": "class",
                "_value": "",
                "_type": "kv",
                "_attrDef": "p"
            },
            {
                "2": false,
                "_key": "fxFlex",
                "_value": "100",
                "_type": "kv",
                "_attrDef": "p"
            },
            {
                "_key": "fxLayoutWrap",
                "_value": "",
                "_type": "kv",
                "_attrDef": "p"
            },
            {
                "_key": "fxLayoutGap",
                "_value": "",
                "_type": "kv",
                "_attrDef": "p"
            },
            {
                "5": false,
                "_key": "fxLayoutAlign",
                "_value": "",
                "_type": "kv",
                "_attrDef": "p"
            },
            {
                "_key": "fxShow",
                "_value": "true",
                "_type": "kv",
                "_attrDef": "p"
            },
            {
                "_key": "fxHide",
                "_value": "false",
                "_type": "kv",
                "_attrDef": "p"
            }
        ],
        "type": 1
    },
    "e7eea1ac-d437-668b-daf3-57317ea4c17c": {
        "name": "NG-button",
        "guid": "e7eea1ac-d437-668b-daf3-57317ea4c17c",
        "template": "<button mat-button %style% %class% %bCustomProps% %color% %(click)%>%buttonname%</button>",
        "designerTemplate": "<div class=\"ad-buttons\"></div>",
        "paletteTemplate": "Button",
        "templateUrl": "https://material.angular.io/components/button/overview",
        "htmlAttributes": [
            {
                "0": false,
                "_key": "style",
                "_value": "  font-size: 19px;",
                "_type": "kv",
                "_attrDef": "p"
            },
            {
                "1": false,
                "_key": "class",
                "_value": "",
                "_type": "kv",
                "_attrDef": "p"
            },
            {
                "2": false,
                "_key": "buttonname",
                "_value": "Register",
                "_type": "a",
                "_attrDef": "p"
            },
            {
                "_key": "color",
                "_value": "",
                "_type": "kv",
                "_attrDef": "p"
            },
            {
                "_key": "(click)",
                "_value": "",
                "_type": "kv",
                "_attrDef": "p"
            }
        ],
        "type": 5
    },
    "28e3b6e9-05b4-ed29-1658-722b60fb0dee": {
        "name": "NG-button",
        "guid": "28e3b6e9-05b4-ed29-1658-722b60fb0dee",
        "template": "<button mat-button %style% %class% %bCustomProps% %color% %(click)%>%buttonname%</button>",
        "designerTemplate": "<div class=\"ad-buttons\"></div>",
        "paletteTemplate": "Button",
        "templateUrl": "https://material.angular.io/components/button/overview",
        "htmlAttributes": [
            {
                "0": false,
                "_key": "style",
                "_value": "  font-size: 19px;",
                "_type": "kv",
                "_attrDef": "p"
            },
            {
                "_key": "class",
                "_value": "",
                "_type": "kv",
                "_attrDef": "p"
            },
            {
                "2": false,
                "_key": "buttonname",
                "_value": "Login",
                "_type": "a",
                "_attrDef": "p"
            },
            {
                "_key": "color",
                "_value": "",
                "_type": "kv",
                "_attrDef": "p"
            },
            {
                "4": false,
                "_key": "(click)",
                "_value": "",
                "_type": "kv",
                "_attrDef": "p"
            }
        ],
        "type": 5
    },
    "b5c08e64-2e5a-90bb-2329-44a0a7530154": {
        "name": "FlexLayoutRow",
        "guid": "b5c08e64-2e5a-90bb-2329-44a0a7530154",
        "template": "<div fxLayout=\"row\" %style% %class% %fxFlex% %fxLayoutWrap% %fxLayoutGap% %fxLayoutAlign% %fxShow% %fxHide% %bCustomProps%></div>",
        "designerTemplate": "<div class=\"row drop bkeeper-container-label\"></div>",
        "paletteTemplate": "Flex Layout Row",
        "templateUrl": "https://github.com/angular/flex-layout/wiki/fxLayout-API",
        "htmlAttributes": [
            {
                "_key": "style",
                "_value": "",
                "_type": "kv",
                "_attrDef": "p"
            },
            {
                "1": false,
                "_key": "class",
                "_value": "",
                "_type": "kv",
                "_attrDef": "p"
            },
            {
                "2": false,
                "_key": "fxFlex",
                "_value": "100",
                "_type": "kv",
                "_attrDef": "p"
            },
            {
                "_key": "fxLayoutWrap",
                "_value": "",
                "_type": "kv",
                "_attrDef": "p"
            },
            {
                "_key": "fxLayoutGap",
                "_value": "",
                "_type": "kv",
                "_attrDef": "p"
            },
            {
                "5": false,
                "_key": "fxLayoutAlign",
                "_value": "",
                "_type": "kv",
                "_attrDef": "p"
            },
            {
                "6": false,
                "_key": "fxShow",
                "_value": "true",
                "_type": "kv",
                "_attrDef": "p"
            },
            {
                "_key": "fxHide",
                "_value": "false",
                "_type": "kv",
                "_attrDef": "p"
            }
        ],
        "type": 1
    },
    "796d5489-f966-e0a4-a3f9-82c2c90327f4": {
        "name": "NG-button",
        "guid": "796d5489-f966-e0a4-a3f9-82c2c90327f4",
        "template": "<button mat-button %style% %class% %bCustomProps% %color% %(click)%>%buttonname%</button>",
        "designerTemplate": "<div class=\"ad-buttons\"></div>",
        "paletteTemplate": "Button",
        "templateUrl": "https://material.angular.io/components/button/overview",
        "htmlAttributes": [
            {
                "0": false,
                "_key": "style",
                "_value": "    font-size: 19px;    margin-left: -3%;",
                "_type": "kv",
                "_attrDef": "p"
            },
            {
                "1": false,
                "_key": "class",
                "_value": "",
                "_type": "kv",
                "_attrDef": "p"
            },
            {
                "2": false,
                "_key": "buttonname",
                "_value": "9600569582",
                "_type": "a",
                "_attrDef": "p"
            },
            {
                "3": false,
                "_key": "color",
                "_value": "",
                "_type": "kv",
                "_attrDef": "p"
            },
            {
                "4": false,
                "_key": "(click)",
                "_value": "",
                "_type": "kv",
                "_attrDef": "p"
            }
        ],
        "type": 5
    },
    "a2b82ac5-f8e5-7c09-b476-bbd72635d032": {
        "name": "NG-button",
        "guid": "a2b82ac5-f8e5-7c09-b476-bbd72635d032",
        "template": "<button mat-button %style% %class% %bCustomProps% %color% %(click)%>%buttonname%</button>",
        "designerTemplate": "<div class=\"ad-buttons\"></div>",
        "paletteTemplate": "Button",
        "templateUrl": "https://material.angular.io/components/button/overview",
        "htmlAttributes": [
            {
                "0": false,
                "_key": "style",
                "_value": "  font-size: 19px;margin-left: -3%;",
                "_type": "kv",
                "_attrDef": "p"
            },
            {
                "1": false,
                "_key": "class",
                "_value": "",
                "_type": "kv",
                "_attrDef": "p"
            },
            {
                "2": false,
                "_key": "buttonname",
                "_value": "hello@roost.com",
                "_type": "a",
                "_attrDef": "p"
            },
            {
                "3": false,
                "_key": "color",
                "_value": "",
                "_type": "kv",
                "_attrDef": "p"
            },
            {
                "4": false,
                "_key": "(click)",
                "_value": "",
                "_type": "kv",
                "_attrDef": "p"
            }
        ],
        "type": 5
    },
    "05c0281a-4741-d687-03f7-62af0b2cdf7b": {
        "name": "NG-image",
        "guid": "05c0281a-4741-d687-03f7-62af0b2cdf7b",
        "template": "<img %imgSrc% %alt% %style% %bCustomProps% %class%>",
        "designerTemplate": "<div class=\"ad-image-component ad-charts-border ad-charts-align bkeeper-container-label\"></div>",
        "paletteTemplate": "Image",
        "templateUrl": "https://www.w3schools.com/html/html_images.asp",
        "htmlAttributes": [
            {
                "_key": "style",
                "_value": "",
                "_type": "kv",
                "_attrDef": "p"
            },
            {
                "1": false,
                "_key": "class",
                "_value": "google",
                "_type": "kv",
                "_attrDef": "p"
            },
            {
                "2": false,
                "_key": "imgSrc",
                "_value": "Web/google-plus-64.png",
                "_type": "kv",
                "_attrDef": "p"
            },
            {
                "_key": "alt",
                "_value": "",
                "_type": "kv",
                "_attrDef": "p"
            }
        ],
        "type": 5
    },
    "84a5394d-9d2c-d714-1622-139d5f9c3b1f": {
        "name": "NG-image",
        "guid": "84a5394d-9d2c-d714-1622-139d5f9c3b1f",
        "template": "<img %imgSrc% %alt% %style% %bCustomProps% %class%>",
        "designerTemplate": "<div class=\"ad-image-component ad-charts-border ad-charts-align bkeeper-container-label\"></div>",
        "paletteTemplate": "Image",
        "templateUrl": "https://www.w3schools.com/html/html_images.asp",
        "htmlAttributes": [
            {
                "_key": "style",
                "_value": "",
                "_type": "kv",
                "_attrDef": "p"
            },
            {
                "1": false,
                "_key": "class",
                "_value": "facebook",
                "_type": "kv",
                "_attrDef": "p"
            },
            {
                "2": false,
                "_key": "imgSrc",
                "_value": "Web/facebook-64.png",
                "_type": "kv",
                "_attrDef": "p"
            },
            {
                "3": false,
                "_key": "alt",
                "_value": "",
                "_type": "kv",
                "_attrDef": "p"
            }
        ],
        "type": 5
    },
    "e974603a-7146-e7a0-906b-80b8cc80294b": {
        "name": "NG-image",
        "guid": "e974603a-7146-e7a0-906b-80b8cc80294b",
        "template": "<img %imgSrc% %alt% %style% %bCustomProps% %class%>",
        "designerTemplate": "<div class=\"ad-image-component ad-charts-border ad-charts-align bkeeper-container-label\"></div>",
        "paletteTemplate": "Image",
        "templateUrl": "https://www.w3schools.com/html/html_images.asp",
        "htmlAttributes": [
            {
                "_key": "style",
                "_value": "",
                "_type": "kv",
                "_attrDef": "p"
            },
            {
                "1": false,
                "_key": "class",
                "_value": "twitter",
                "_type": "kv",
                "_attrDef": "p"
            },
            {
                "2": false,
                "_key": "imgSrc",
                "_value": "Web/twitter-64.png",
                "_type": "kv",
                "_attrDef": "p"
            },
            {
                "3": false,
                "_key": "alt",
                "_value": "",
                "_type": "kv",
                "_attrDef": "p"
            }
        ],
        "type": 5
    },
    "e3612636-0718-b981-33b8-ca924a194684": {
        "name": "FlexLayoutRow",
        "guid": "e3612636-0718-b981-33b8-ca924a194684",
        "template": "<div fxLayout=\"row\" %style% %class% %fxFlex% %fxLayoutWrap% %fxLayoutGap% %fxLayoutAlign% %fxShow% %fxHide% %bCustomProps%></div>",
        "designerTemplate": "<div class=\"row drop bkeeper-container-label\"></div>",
        "paletteTemplate": "Flex Layout Row",
        "templateUrl": "https://github.com/angular/flex-layout/wiki/fxLayout-API",
        "htmlAttributes": [
            {
                "_key": "style",
                "_value": "",
                "_type": "kv",
                "_attrDef": "p"
            },
            {
                "1": false,
                "_key": "class",
                "_value": "",
                "_type": "kv",
                "_attrDef": "p"
            },
            {
                "2": false,
                "_key": "fxFlex",
                "_value": "",
                "_type": "kv",
                "_attrDef": "p"
            },
            {
                "_key": "fxLayoutWrap",
                "_value": "",
                "_type": "kv",
                "_attrDef": "p"
            },
            {
                "_key": "fxLayoutGap",
                "_value": "",
                "_type": "kv",
                "_attrDef": "p"
            },
            {
                "5": false,
                "_key": "fxLayoutAlign",
                "_value": "",
                "_type": "kv",
                "_attrDef": "p"
            },
            {
                "6": false,
                "_key": "fxShow",
                "_value": "true",
                "_type": "kv",
                "_attrDef": "p"
            },
            {
                "_key": "fxHide",
                "_value": "false",
                "_type": "kv",
                "_attrDef": "p"
            }
        ],
        "type": 1
    },
    "c6547b7f-ae4b-f3a0-92d7-e3598f76d2b7": {
        "name": "FlexLayoutRow",
        "guid": "c6547b7f-ae4b-f3a0-92d7-e3598f76d2b7",
        "template": "<div fxLayout=\"row\" %style% %class% %fxFlex% %fxLayoutWrap% %fxLayoutGap% %fxLayoutAlign% %fxShow% %fxHide% %bCustomProps%></div>",
        "designerTemplate": "<div class=\"row drop bkeeper-container-label\"></div>",
        "paletteTemplate": "Flex Layout Row",
        "templateUrl": "https://github.com/angular/flex-layout/wiki/fxLayout-API",
        "htmlAttributes": [
            {
                "0": false,
                "_key": "style",
                "_value": "padding:2%",
                "_type": "kv",
                "_attrDef": "p"
            },
            {
                "1": false,
                "_key": "class",
                "_value": "",
                "_type": "kv",
                "_attrDef": "p"
            },
            {
                "2": false,
                "_key": "fxFlex",
                "_value": "none",
                "_type": "kv",
                "_attrDef": "p"
            },
            {
                "_key": "fxLayoutWrap",
                "_value": "",
                "_type": "kv",
                "_attrDef": "p"
            },
            {
                "4": false,
                "_key": "fxLayoutGap",
                "_value": "",
                "_type": "kv",
                "_attrDef": "p"
            },
            {
                "5": false,
                "_key": "fxLayoutAlign",
                "_value": "center center",
                "_type": "kv",
                "_attrDef": "p"
            },
            {
                "6": false,
                "_key": "fxShow",
                "_value": "true",
                "_type": "kv",
                "_attrDef": "p"
            },
            {
                "_key": "fxHide",
                "_value": "false",
                "_type": "kv",
                "_attrDef": "p"
            }
        ],
        "type": 1
    },
    "6a63bfce-3406-e79f-f71b-fcb204746414": {
        "name": "NG-Input",
        "guid": "6a63bfce-3406-e79f-f71b-fcb204746414",
        "template": "<mat-form-field %color% %style% %class%><input matInput  %[(ngModel)]% %name% %type% %placeholder% %value% %required% %bCustomProps%></mat-form-field>",
        "designerTemplate": "<div class=\"ad-textfield ad-height\">text</div>",
        "paletteTemplate": "Input",
        "templateUrl": "https://material.angular.io/components/input/overview",
        "htmlAttributes": [
            {
                "0": false,
                "_key": "style",
                "_value": "margin-top: 8%;background-color:white;   font-size: 14px !important;  height: 41px !important;        width: 593px;",
                "_type": "kv",
                "_attrDef": "p"
            },
            {
                "1": false,
                "_key": "class",
                "_value": "hidePlaceHolder",
                "_type": "kv",
                "_attrDef": "p"
            },
            {
                "2": false,
                "_key": "placeholder",
                "_value": "Enter any feature",
                "_type": "kv",
                "_attrDef": "p"
            },
            {
                "3": false,
                "_key": "value",
                "_value": "",
                "_type": "kv",
                "_attrDef": "p"
            },
            {
                "4": false,
                "_key": "required",
                "_value": "",
                "_type": "a",
                "_attrDef": "p"
            },
            {
                "5": false,
                "_key": "[(ngModel)]",
                "_value": "",
                "_type": "kv",
                "_attrDef": "p"
            },
            {
                "6": false,
                "_key": "color",
                "_value": "",
                "_type": "kv",
                "_attrDef": "p"
            },
            {
                "7": false,
                "_key": "name",
                "_value": "",
                "_type": "kv",
                "_attrDef": "p"
            },
            {
                "8": false,
                "_key": "type",
                "_value": "",
                "_type": "kv",
                "_attrDef": "p"
            }
        ],
        "type": 5
    },
    "f53191bd-310a-0652-42c0-3315ee235b14": {
        "name": "NG-Footer",
        "guid": "f53191bd-310a-0652-42c0-3315ee235b14",
        "template": "<footer %style% %class% %bCustomProps%></footer>",
        "designerTemplate": "<div class=\"ad-footer ad-charts-border drop bkeeper-container-label\"></div>",
        "paletteTemplate": "Footer",
        "templateUrl": "https://www.w3schools.com/tags/tag_footer.asp",
        "htmlAttributes": [
            {
                "0": false,
                "_key": "style",
                "_value": "",
                "_type": "kv",
                "_attrDef": "p"
            },
            {
                "1": false,
                "_key": "class",
                "_value": "",
                "_type": "kv",
                "_attrDef": "p"
            }
        ],
        "type": 1
    },
    "afc6f68e-e7f4-1002-7fa4-8ad5d1526c99": {
        "name": "NG-Paragraph",
        "guid": "afc6f68e-e7f4-1002-7fa4-8ad5d1526c99",
        "template": "<p %bCustomProps% %style% %class%>%text%</p>",
        "designerTemplate": "<div class=\"ad-header-elements ad-h3\">p</div>",
        "paletteTemplate": "Paragraph",
        "templateUrl": "https://www.w3schools.com/tags/tag_p.asp",
        "htmlAttributes": [
            {
                "0": false,
                "_key": "style",
                "_value": "",
                "_type": "kv",
                "_attrDef": "p"
            },
            {
                "1": false,
                "_key": "class",
                "_value": "",
                "_type": "kv",
                "_attrDef": "p"
            },
            {
                "2": false,
                "_key": "text",
                "_value": "Copyright © 2018 Neutrinos",
                "_type": "a",
                "_attrDef": "p"
            }
        ],
        "type": 5
    },
    "425bee94-f125-73b9-bf8f-e48f1095db7a": {
        "name": "FlexLayoutRow",
        "guid": "425bee94-f125-73b9-bf8f-e48f1095db7a",
        "template": "<div fxLayout=\"row\" %style% %class% %fxFlex% %fxLayoutWrap% %fxLayoutGap% %fxLayoutAlign% %fxShow% %fxHide% %bCustomProps%></div>",
        "designerTemplate": "<div class=\"row drop bkeeper-container-label\"></div>",
        "paletteTemplate": "Flex Layout Row",
        "templateUrl": "https://github.com/angular/flex-layout/wiki/fxLayout-API",
        "htmlAttributes": [
            {
                "0": false,
                "_key": "style",
                "_value": "width:100%",
                "_type": "kv",
                "_attrDef": "p"
            },
            {
                "1": false,
                "_key": "class",
                "_value": "footer",
                "_type": "kv",
                "_attrDef": "p"
            },
            {
                "2": false,
                "_key": "fxFlex",
                "_value": "100",
                "_type": "kv",
                "_attrDef": "p"
            },
            {
                "3": false,
                "_key": "fxLayoutWrap",
                "_value": "",
                "_type": "kv",
                "_attrDef": "p"
            },
            {
                "4": false,
                "_key": "fxLayoutGap",
                "_value": "",
                "_type": "kv",
                "_attrDef": "p"
            },
            {
                "5": false,
                "_key": "fxLayoutAlign",
                "_value": "center center",
                "_type": "kv",
                "_attrDef": "p"
            },
            {
                "6": false,
                "_key": "fxShow",
                "_value": "true",
                "_type": "kv",
                "_attrDef": "p"
            },
            {
                "7": false,
                "_key": "fxHide",
                "_value": "false",
                "_type": "kv",
                "_attrDef": "p"
            }
        ],
        "type": 1
    },
    "768de013-95c6-8520-ab8f-1223447fbd45": {
        "name": "NG-icon",
        "guid": "768de013-95c6-8520-ab8f-1223447fbd45",
        "template": "<mat-icon %style% %class% %bCustomProps%>%IconName%</mat-icon>",
        "designerTemplate": "<div class=\"ad-icon\"><i class=\"material-icons\" style=\"transform:rotate(180deg)\">priority_high</i></div>",
        "paletteTemplate": "Icon",
        "templateUrl": "https://material.angular.io/components/icon/overview",
        "htmlAttributes": [
            {
                "0": false,
                "_key": "style",
                "_value": "",
                "_type": "kv",
                "_attrDef": "p"
            },
            {
                "1": false,
                "_key": "class",
                "_value": "phone",
                "_type": "kv",
                "_attrDef": "p"
            },
            {
                "2": false,
                "_key": "IconName",
                "_value": "phone",
                "_type": "a",
                "_attrDef": "p"
            }
        ],
        "type": 5
    },
    "eb214a8a-ff4d-a94d-8c38-f39120f9d6fc": {
        "name": "NG-icon",
        "guid": "eb214a8a-ff4d-a94d-8c38-f39120f9d6fc",
        "template": "<mat-icon %style% %class% %bCustomProps%>%IconName%</mat-icon>",
        "designerTemplate": "<div class=\"ad-icon\"><i class=\"material-icons\" style=\"transform:rotate(180deg)\">priority_high</i></div>",
        "paletteTemplate": "Icon",
        "templateUrl": "https://material.angular.io/components/icon/overview",
        "htmlAttributes": [
            {
                "0": false,
                "_key": "style",
                "_value": "",
                "_type": "kv",
                "_attrDef": "p"
            },
            {
                "1": false,
                "_key": "class",
                "_value": "",
                "_type": "kv",
                "_attrDef": "p"
            },
            {
                "2": false,
                "_key": "IconName",
                "_value": "mail",
                "_type": "a",
                "_attrDef": "p"
            }
        ],
        "type": 5
    },
    "1eb16bd6-65bb-1ea2-8e5e-4c9f4490f498": {
        "name": "FlexLayoutCol",
        "guid": "1eb16bd6-65bb-1ea2-8e5e-4c9f4490f498",
        "template": "<div fxLayout=\"column\" %style% %class% %fxFlex% %fxLayoutWrap% %fxLayoutGap% %fxLayoutAlign% %fxShow% %fxHide% %bCustomProps%></div>",
        "designerTemplate": "<div class=\"column drop bkeeper-container-label\"></div>",
        "paletteTemplate": "Flex Layout Column",
        "templateUrl": "https://github.com/angular/flex-layout/wiki/fxLayout-API",
        "htmlAttributes": [
            {
                "0": false,
                "_key": "style",
                "_value": "",
                "_type": "kv",
                "_attrDef": "p"
            },
            {
                "1": false,
                "_key": "class",
                "_value": "",
                "_type": "kv",
                "_attrDef": "p"
            },
            {
                "2": false,
                "_key": "fxFlex",
                "_value": "",
                "_type": "kv",
                "_attrDef": "p"
            },
            {
                "3": false,
                "_key": "fxLayoutWrap",
                "_value": "",
                "_type": "kv",
                "_attrDef": "p"
            },
            {
                "4": false,
                "_key": "fxLayoutGap",
                "_value": "",
                "_type": "kv",
                "_attrDef": "p"
            },
            {
                "5": false,
                "_key": "fxLayoutAlign",
                "_value": "start start",
                "_type": "kv",
                "_attrDef": "p"
            },
            {
                "6": false,
                "_key": "fxShow",
                "_value": "true",
                "_type": "kv",
                "_attrDef": "p"
            },
            {
                "7": false,
                "_key": "fxHide",
                "_value": "false",
                "_type": "kv",
                "_attrDef": "p"
            },
            {
                "_key": "fxHide.gt-xs",
                "_value": "true",
                "_type": "kv",
                "_attrDef": "c"
            },
            {
                "_key": "fxFlex.xs",
                "_value": "50",
                "_type": "kv",
                "_attrDef": "c"
            },
            {
                "_key": "fxFlex.gt-xs",
                "_value": "0",
                "_type": "kv",
                "_attrDef": "c"
            }
        ],
        "type": 1
    },
    "228f76e6-ebf2-dd15-411f-1bc9a2670a89": {
        "name": "NG-icon",
        "guid": "228f76e6-ebf2-dd15-411f-1bc9a2670a89",
        "template": "<mat-icon %style% %class% %bCustomProps%>%IconName%</mat-icon>",
        "designerTemplate": "<div class=\"ad-icon\"><i class=\"material-icons\" style=\"transform:rotate(180deg)\">priority_high</i></div>",
        "paletteTemplate": "Icon",
        "templateUrl": "https://material.angular.io/components/icon/overview",
        "htmlAttributes": [
            {
                "0": false,
                "_key": "style",
                "_value": "cursor:pointer;",
                "_type": "kv",
                "_attrDef": "p"
            },
            {
                "1": false,
                "_key": "class",
                "_value": "menu",
                "_type": "kv",
                "_attrDef": "p"
            },
            {
                "2": false,
                "_key": "IconName",
                "_value": "menu",
                "_type": "a",
                "_attrDef": "p"
            },
            {
                "3": false,
                "_key": "(click)",
                "_value": "sidenav.toggle()",
                "_type": "kv",
                "_attrDef": "c"
            }
        ],
        "type": 5
    },
    "fbb7f237-0c67-2708-9da9-2020bccff78b": {
        "name": "NG-sidenav-container",
        "guid": "fbb7f237-0c67-2708-9da9-2020bccff78b",
        "template": "<mat-sidenav-container %style% %bCustomProps% %class%></mat-sidenav-container>",
        "designerTemplate": "<div class=\"ad-sidenav-container ad-charts-border drop bkeeper-container-label\"><i style=\"font-size: 20px;position:absolute !important;top:0%;left:100px;\" class=\"material-icons validate icons-events\">content_paste</i></div>",
        "paletteTemplate": "Sidenav Container",
        "templateUrl": "https://material.angular.io/components/sidenav/overview",
        "htmlAttributes": [
            {
                "0": false,
                "_key": "style",
                "_value": "  background-color: #3F51B5;",
                "_type": "kv",
                "_attrDef": "p"
            },
            {
                "1": false,
                "_key": "class",
                "_value": "",
                "_type": "kv",
                "_attrDef": "p"
            },
            {
                "2": false,
                "_key": "fullscreen",
                "_value": "fullscreen",
                "_type": "kv",
                "_attrDef": "c"
            }
        ],
        "type": 6
    },
    "5a2d9f0a-e83c-dff1-e004-90c82fb5efef": {
        "name": "NG-sidenav",
        "guid": "5a2d9f0a-e83c-dff1-e004-90c82fb5efef",
        "template": "<mat-sidenav #sidenav %bCustomProps% %style% %class% %fxLayout% %mode% %(open)% %(close)% %(toggle)% %align% %opened%></mat-sidenav>",
        "designerTemplate": "<div class=\"ad-side-nav1 ad-charts-border drop bkeeper-container-label\"><div class=\"icon-events ad-side-nav1-image\"></div></div>",
        "paletteTemplate": "Sidenav",
        "templateUrl": "https://material.angular.io/components/sidenav/overview",
        "htmlAttributes": [
            {
                "0": false,
                "_key": "style",
                "_value": "  top: 56px;",
                "_type": "kv",
                "_attrDef": "p"
            },
            {
                "1": false,
                "_key": "class",
                "_value": "sidenav",
                "_type": "kv",
                "_attrDef": "p"
            },
            {
                "2": false,
                "_key": "mode",
                "_value": "",
                "_type": "kv",
                "_attrDef": "p"
            },
            {
                "3": false,
                "_key": "opened",
                "_value": "",
                "_type": "kv",
                "_attrDef": "p"
            },
            {
                "4": false,
                "_key": "align",
                "_value": "",
                "_type": "kv",
                "_attrDef": "p"
            },
            {
                "5": false,
                "_key": "fxLayout",
                "_value": "",
                "_type": "kv",
                "_attrDef": "p"
            },
            {
                "6": false,
                "_key": "(open)",
                "_value": "",
                "_type": "kv",
                "_attrDef": "p"
            },
            {
                "7": false,
                "_key": "(close)",
                "_value": "",
                "_type": "kv",
                "_attrDef": "p"
            },
            {
                "8": false,
                "_key": "(toggle)",
                "_value": "sidenav.toggle()",
                "_type": "kv",
                "_attrDef": "p"
            },
            {
                "9": false,
                "_key": "[(opened)]",
                "_value": "opened",
                "_type": "kv",
                "_attrDef": "c"
            }
        ],
        "type": 6
    },
    "d39c9cf5-0853-aaef-b081-ea2b5d702428": {
        "name": "FlexLayoutCol",
        "guid": "d39c9cf5-0853-aaef-b081-ea2b5d702428",
        "template": "<div fxLayout=\"column\" %style% %class% %fxFlex% %fxLayoutWrap% %fxLayoutGap% %fxLayoutAlign% %fxShow% %fxHide% %bCustomProps%></div>",
        "designerTemplate": "<div class=\"column drop bkeeper-container-label\"></div>",
        "paletteTemplate": "Flex Layout Column",
        "templateUrl": "https://github.com/angular/flex-layout/wiki/fxLayout-API",
        "htmlAttributes": [
            {
                "_key": "style",
                "_value": "",
                "_type": "kv",
                "_attrDef": "p"
            },
            {
                "_key": "class",
                "_value": "",
                "_type": "kv",
                "_attrDef": "p"
            },
            {
                "_key": "fxFlex",
                "_value": "",
                "_type": "kv",
                "_attrDef": "p"
            },
            {
                "_key": "fxLayoutWrap",
                "_value": "",
                "_type": "kv",
                "_attrDef": "p"
            },
            {
                "_key": "fxLayoutGap",
                "_value": "",
                "_type": "kv",
                "_attrDef": "p"
            },
            {
                "_key": "fxLayoutAlign",
                "_value": "",
                "_type": "kv",
                "_attrDef": "p"
            },
            {
                "_key": "fxShow",
                "_value": "true",
                "_type": "kv",
                "_attrDef": "p"
            },
            {
                "_key": "fxHide",
                "_value": "false",
                "_type": "kv",
                "_attrDef": "p"
            }
        ],
        "type": 1
    },
    "dc8a6329-6c4e-db46-80d6-e09ea4788ac8": {
        "name": "NG-list",
        "guid": "dc8a6329-6c4e-db46-80d6-e09ea4788ac8",
        "template": "<mat-list %style% %bCustomProps% %class%></mat-list>",
        "designerTemplate": "<div class=\"ad-list-border drop ad-list\"></div>",
        "paletteTemplate": "List",
        "templateUrl": "https://material.angular.io/components/list/overview",
        "htmlAttributes": [
            {
                "0": true,
                "_key": "style",
                "_value": "",
                "_type": "kv",
                "_attrDef": "p"
            },
            {
                "_key": "class",
                "_value": "",
                "_type": "kv",
                "_attrDef": "p"
            }
        ],
        "type": 1
    },
    "a0e3e941-571d-a23b-d263-780d1c18b0de": {
        "name": "NG-listItem",
        "guid": "a0e3e941-571d-a23b-d263-780d1c18b0de",
        "template": "<mat-list-item %*ngFor%  %style% %bCustomProps% %class%>%label%</mat-list-item>",
        "designerTemplate": "<div class=\"ad-list-border  drop ad-list ad-list-item\"></div>",
        "paletteTemplate": "List Item",
        "templateUrl": "https://material.angular.io/components/list/overview",
        "htmlAttributes": [
            {
                "0": false,
                "_key": "style",
                "_value": "color:white;cursor:pointer;",
                "_type": "kv",
                "_attrDef": "p"
            },
            {
                "1": false,
                "_key": "class",
                "_value": "",
                "_type": "kv",
                "_attrDef": "p"
            },
            {
                "2": false,
                "_key": "*ngFor",
                "_value": "",
                "_type": "kv",
                "_attrDef": "p"
            },
            {
                "3": false,
                "_key": "label",
                "_value": "Home",
                "_type": "a",
                "_attrDef": "p"
            }
        ],
        "type": 1
    },
    "39c0a6ec-dcc2-bb5a-6156-91266a924480": {
        "name": "NG-listItem",
        "guid": "39c0a6ec-dcc2-bb5a-6156-91266a924480",
        "template": "<mat-list-item %*ngFor%  %style% %bCustomProps% %class%>%label%</mat-list-item>",
        "designerTemplate": "<div class=\"ad-list-border  drop ad-list ad-list-item\"></div>",
        "paletteTemplate": "List Item",
        "templateUrl": "https://material.angular.io/components/list/overview",
        "htmlAttributes": [
            {
                "0": false,
                "_key": "style",
                "_value": "color:white;cursor:pointer;",
                "_type": "kv",
                "_attrDef": "p"
            },
            {
                "_key": "class",
                "_value": "",
                "_type": "kv",
                "_attrDef": "p"
            },
            {
                "2": false,
                "_key": "*ngFor",
                "_value": "",
                "_type": "kv",
                "_attrDef": "p"
            },
            {
                "3": false,
                "_key": "label",
                "_value": "Dashboard",
                "_type": "a",
                "_attrDef": "p"
            }
        ],
        "type": 1
    },
    "54f75fff-b85e-3215-6ad1-3fa9c6fff5d7": {
        "name": "NG-listItem",
        "guid": "54f75fff-b85e-3215-6ad1-3fa9c6fff5d7",
        "template": "<mat-list-item %*ngFor%  %style% %bCustomProps% %class%>%label%</mat-list-item>",
        "designerTemplate": "<div class=\"ad-list-border  drop ad-list ad-list-item\"></div>",
        "paletteTemplate": "List Item",
        "templateUrl": "https://material.angular.io/components/list/overview",
        "htmlAttributes": [
            {
                "0": false,
                "_key": "style",
                "_value": "color:white;cursor:pointer;",
                "_type": "kv",
                "_attrDef": "p"
            },
            {
                "1": false,
                "_key": "class",
                "_value": "",
                "_type": "kv",
                "_attrDef": "p"
            },
            {
                "2": false,
                "_key": "*ngFor",
                "_value": "",
                "_type": "kv",
                "_attrDef": "p"
            },
            {
                "3": false,
                "_key": "label",
                "_value": "Logout",
                "_type": "a",
                "_attrDef": "p"
            }
        ],
        "type": 1
    }
}
